Metadata-Version: 1.0
Name: kaldi-spotter
Version: 0.1.5
Summary: wake word spotting with kaldi
Home-page: https://github.com/JarbasAl/kaldi_spotter
Author: jarbasAI
Author-email: jarbasai@mailfence.com
License: apache2.0
Platform: UNKNOWN
